{
  "apps": [
    {
      "name": "Inshot (MOD)",
    "icon": "https://i.postimg.cc/4dYsfzn4/download.jpg",
      "size": "78 MB",
      "version": "(MOD)",
      "download": "https://tinyurl.com/2wkv9s5a"
    },
    {
      "name": "ppcine free movies",
    "icon": "https://i.postimg.cc/nLdcXxCy/PPCine-Movie-App-Logo-768x768.webp",
      "size": "43 MB",
      "version": "new",
      "download": "https://www.dl.dropboxusercontent.com/scl/fi/ahhuze2z8gpvhr80oc9fz/PPCine.apk?rlkey=dko6nbpdbr1y85va9rcpumnvf&st=w9pw7fn3"
    },
    {
      "name": "MINI MILITIA-DJFARIS-HACKED",
    "icon": "https://i.postimg.cc/Jz8nQwWP/images.jpg",
      "size": "44 MB",
      "version": "hacked",
      "download": "https://www.dl.dropboxusercontent.com/scl/fi/ayt04zisvjpwz53crjtlj/MINI-MILITIA-DJFARIS-HACKED.apk?rlkey=go5r6ktk3y7uif6gidv2cdrd8&st=hznqmvq0"
    
      
    
    
    
    }
  ]
}
